moncli/__init__.py
moncli/config.py
moncli/enums.py
moncli/error.py
moncli/models.py
moncli/types.py
moncli/api_v1/__init__.py
moncli/api_v1/boards.py
moncli/api_v1/constants.py
moncli/api_v1/pulses.py
moncli/api_v1/requests.py
moncli/api_v1/tags.py
moncli/api_v1/updates.py
moncli/api_v1/users.py
moncli/api_v2/__init__.py
moncli/api_v2/constants.py
moncli/api_v2/exceptions.py
moncli/api_v2/graphql.py
moncli/api_v2/handlers.py
moncli/api_v2/requests.py
moncli/column_value/__init__.py
moncli/column_value/base.py
moncli/column_value/complex.py
moncli/column_value/constants.py
moncli/column_value/objects.py
moncli/column_value/readonly.py
moncli/column_value/simple.py
moncli/entities/__init__.py
moncli/entities/asset.py
moncli/entities/base.py
moncli/entities/board.py
moncli/entities/client.py
moncli/entities/column.py
moncli/entities/group.py
moncli/entities/item.py
moncli/entities/objects.py
moncli/entities/update.py
moncli/entities/user.py
moncli-2.0.14.dist-info/LICENSE
moncli-2.0.14.dist-info/METADATA
moncli-2.0.14.dist-info/WHEEL
moncli-2.0.14.dist-info/top_level.txt
moncli-2.0.14.dist-info/RECORD
