Metadata-Version: 2.1
Name: moncli
Version: 2.0.14
Summary: Moncli, a pythonic/DDD client for Monday.com
Home-page: https://github.com/trix-solutions/moncli
Author: Andrew Shatz, Trix Solutions
Author-email: andrew.shatz@trix.solutions
License: BSD 3
Download-URL: https://github.com/trix-solutions/moncli
Platform: UNKNOWN
License-File: LICENSE
Requires-Dist: requests (>=2.24.0)
Requires-Dist: pytz (>=2020.1)
Requires-Dist: pycountry (>=20.7.3)
Requires-Dist: deprecated (>=1.2.10)
Requires-Dist: schematics (>=2.1.0)
